seismolab/__init__.py
seismolab/version.py
seismolab/OC/OC.py
seismolab/OC/__init__.py
seismolab/OC/shift_curves.py
seismolab/fourier/__init__.py
seismolab/fourier/fourier.py
seismolab/gaia/__init__.py
seismolab/gaia/query_gaia.py
seismolab/gaia/querytools.py
seismolab/inpainting/__init__.py
seismolab/inpainting/inpainting.py
seismolab/inpainting/tools.py
seismolab/inpainting/Exec_C++/cb_mca1d_Linux_32
seismolab/inpainting/Exec_C++/cb_mca1d_Linux_64
seismolab/inpainting/Exec_C++/cb_mca1d_MacOSX_Intel_32
seismolab/inpainting/Exec_C++/cb_mca1d_MacOSX_Intel_64
seismolab/template/__init__.py
seismolab/template/template.py
seismolab/tfa/__init__.py
seismolab/tfa/choi_williams.py
seismolab/tfa/gabor.py
seismolab/tfa/tools.py
seismolab/tfa/wavelet.py
seismolab/tfa/windowed_lomb_scargle.py
seismolab-1.1.4.dist-info/LICENCE
seismolab-1.1.4.dist-info/METADATA
seismolab-1.1.4.dist-info/WHEEL
seismolab-1.1.4.dist-info/entry_points.txt
seismolab-1.1.4.dist-info/top_level.txt
seismolab-1.1.4.dist-info/RECORD
