Metadata-Version: 2.1
Name: seismolab
Version: 1.1.4
Summary: Open-source python framework for downloading, analyzing, and visualizing data of variable stars from space-based surveys.
Home-page: https://github.com/konkolyseismolab/
Author: Attila Bodi
Author-email: bodi.attila@csfk.org
Classifier: Development Status :: 3 - Alpha
Classifier: License :: OSI Approved :: MIT License
Classifier: Natural Language :: English
Classifier: Operating System :: MacOS :: MacOS X
Classifier: Operating System :: Unix
Classifier: Programming Language :: Python
Requires-Python: >=3.10
License-File: LICENCE
Requires-Dist: numpy<2.0,>=1.4.0
Requires-Dist: scipy>=1.7.0
Requires-Dist: matplotlib>=3.5
Requires-Dist: astropy>=4.1rc1
Requires-Dist: tqdm>=4.25.0
Requires-Dist: uncertainties
Requires-Dist: corner
Requires-Dist: joblib
Requires-Dist: pandas>=1.3
Requires-Dist: psutil
Requires-Dist: h5py
Requires-Dist: ephem
Requires-Dist: astroquery
Requires-Dist: numpydoc
Requires-Dist: nbsphinx
Requires-Dist: statsmodels
Requires-Dist: pymc
Requires-Dist: pyvo
Requires-Dist: seaborn
Requires-Dist: regex
Requires-Dist: requests
Requires-Dist: mwdust
Requires-Dist: arviz
Provides-Extra: test
Requires-Dist: pytest; extra == "test"
Requires-Dist: pytest-cov; extra == "test"
